Workbook
Name Cat_Modulos: Catalogos!$D$3:$D$8
Name Cat_Etapas: Catalogos!$J$3:$J$8
Name Cat_Areas: Catalogos!$H$3:$H$10
Name Cat_Estatus: Catalogos!$A$3:$A$7
Name Cat_Factor: Catalogos!$B$3:$B$7
Name Cat_Prioridad: Catalogos!$F$3:$F$6

Sheet Resumen_Ejecutivo
A1: TABLERO DE CONTROL — PLANTILLAS DE MIGRACIÓN ORACLE NETSUITE
A2: GRUPO ESTEVEZ · Etapa vigente: llenado de plantillas por áreas y Key Users
A3: =" Actualizado al: "&TEXT(TODAY(),"DD/MM/YYYY") -> Actualizado al: 12/10/2026
A5: INDICADORES CLAVE | E5: AVANCE POR MÓDULO
A6: Plantillas totales | C6: =COUNTA(Control_Plantillas!$A$4:$A$59) -> 41 | E6: Módulo | F6: Plantillas | G6: % Avance | H6: E1 Llenado OK | I6: E2 Revisión OK | J6: E3 Repositorio OK | K6: E4 Sandbox OK | L6: E5 Productivo OK
A7: Avance global ponderado | C7: =IFERROR(AVERAGE(Control_Plantillas!$Z$4:$Z$59),0) -> 0.47195122 | E7: Finanzas (R2R) | F7: =COUNTIF(Control_Plantillas!$B$4:$B$59,$E7) -> 6 | G7: =IFERROR(AVERAGEIF(Control_Plantillas!$B$4:$B$59,$E7,Control_Plantillas!$Z$4:$Z$59),0) -> 0.75 | H7: =COUNTIFS(Control_Plantillas!$B$4:$B$59,$E7,Control_Plantillas!$I$4:$I$59,"Completado") -> 6 | I7: =COUNTIFS(Control_Plantillas!$B$4:$B$59,$E7,Control_Plantillas!$L$4:$L$59,"Completado") -> 6 | J7: =COUNTIFS(Control_Plantillas!$B$4:$B$59,$E7,Control_Plantillas!$O$4:$O$59,"Completado") -> 6 | K7: =COUNTIFS(Control_Plantillas!$B$4:$B$59,$E7,Control_Plantillas!$R$4:$R$59,"Completado") -> 0 | L7: =COUNTIFS(Control_Plantillas!$B$4:$B$59,$E7,Control_Plantillas!$U$4:$U$59,"Completado") -> 0
A8: Llenado completado | C8: =COUNTIF(Control_Plantillas!$I$4:$I$59,"Completado") -> 23 | E8: Compras (P2P) | F8: =COUNTIF(Control_Plantillas!$B$4:$B$59,$E8) -> 2 | G8: =IFERROR(AVERAGEIF(Control_Plantillas!$B$4:$B$59,$E8,Control_Plantillas!$Z$4:$Z$59),0) -> 0.75 | H8: =COUNTIFS(Control_Plantillas!$B$4:$B$59,$E8,Control_Plantillas!$I$4:$I$59,"Completado") -> 2 | I8: =COUNTIFS(Control_Plantillas!$B$4:$B$59,$E8,Control_Plantillas!$L$4:$L$59,"Completado") -> 2 | J8: =COUNTIFS(Control_Plantillas!$B$4:$B$59,$E8,Control_Plantillas!$O$4:$O$59,"Completado") -> 2 | K8: =COUNTIFS(Control_Plantillas!$B$4:$B$59,$E8,Control_Plantillas!$R$4:$R$59,"Completado") -> 0 | L8: =COUNTIFS(Control_Plantillas!$B$4:$B$59,$E8,Control_Plantillas!$U$4:$U$59,"Completado") -> 0
A9: Llenado en proceso | C9: =COUNTIF(Control_Plantillas!$I$4:$I$59,"En proceso") -> 18 | E9: Ventas (O2C) | F9: =COUNTIF(Control_Plantillas!$B$4:$B$59,$E9) -> 3 | G9: =IFERROR(AVERAGEIF(Control_Plantillas!$B$4:$B$59,$E9,Control_Plantillas!$Z$4:$Z$59),0) -> 0.75 | H9: =COUNTIFS(Control_Plantillas!$B$4:$B$59,$E9,Control_Plantillas!$I$4:$I$59,"Completado") -> 3 | I9: =COUNTIFS(Control_Plantillas!$B$4:$B$59,$E9,Control_Plantillas!$L$4:$L$59,"Completado") -> 3 | J9: =COUNTIFS(Control_Plantillas!$B$4:$B$59,$E9,Control_Plantillas!$O$4:$O$59,"Completado") -> 3 | K9: =COUNTIFS(Control_Plantillas!$B$4:$B$59,$E9,Control_Plantillas!$R$4:$R$59,"Completado") -> 0 | L9: =COUNTIFS(Control_Plantillas!$B$4:$B$59,$E9,Control_Plantillas!$U$4:$U$59,"Completado") -> 0
A10: Sin iniciar | C10: =COUNTIF(Control_Plantillas!$I$4:$I$59,"No iniciado") -> 0 | E10: Inventarios (D2B) | F10: =COUNTIF(Control_Plantillas!$B$4:$B$59,$E10) -> 23 | G10: =IFERROR(AVERAGEIF(Control_Plantillas!$B$4:$B$59,$E10,Control_Plantillas!$Z$4:$Z$59),0) -> 0.26521739 | H10: =COUNTIFS(Control_Plantillas!$B$4:$B$59,$E10,Control_Plantillas!$I$4:$I$59,"Completado") -> 5 | I10: =COUNTIFS(Control_Plantillas!$B$4:$B$59,$E10,Control_Plantillas!$L$4:$L$59,"Completado") -> 0 | J10: =COUNTIFS(Control_Plantillas!$B$4:$B$59,$E10,Control_Plantillas!$O$4:$O$59,"Completado") -> 0 | K10: =COUNTIFS(Control_Plantillas!$B$4:$B$59,$E10,Control_Plantillas!$R$4:$R$59,"Completado") -> 0 | L10: =COUNTIFS(Control_Plantillas!$B$4:$B$59,$E10,Control_Plantillas!$U$4:$U$59,"Completado") -> 0
A11: Bloqueadas | C11: =COUNTIF(Control_Plantillas!$AC$4:$AC$59,"Bloqueado") -> 0 | E11: Manufactura (MFG) | F11: =COUNTIF(Control_Plantillas!$B$4:$B$59,$E11) -> 6 | G11: =IFERROR(AVERAGEIF(Control_Plantillas!$B$4:$B$59,$E11,Control_Plantillas!$Z$4:$Z$59),0) -> 0.75 | H11: =COUNTIFS(Control_Plantillas!$B$4:$B$59,$E11,Control_Plantillas!$I$4:$I$59,"Completado") -> 6 | I11: =COUNTIFS(Control_Plantillas!$B$4:$B$59,$E11,Control_Plantillas!$L$4:$L$59,"Completado") -> 6 | J11: =COUNTIFS(Control_Plantillas!$B$4:$B$59,$E11,Control_Plantillas!$O$4:$O$59,"Completado") -> 6 | K11: =COUNTIFS(Control_Plantillas!$B$4:$B$59,$E11,Control_Plantillas!$R$4:$R$59,"Completado") -> 0 | L11: =COUNTIFS(Control_Plantillas!$B$4:$B$59,$E11,Control_Plantillas!$U$4:$U$59,"Completado") -> 0
A12: Vencidas | C12: =COUNTIF(Control_Plantillas!$AC$4:$AC$59,"Vencido") -> 24 | E12: Activos Fijos (FA) | F12: =COUNTIF(Control_Plantillas!$B$4:$B$59,$E12) -> 1 | G12: =IFERROR(AVERAGEIF(Control_Plantillas!$B$4:$B$59,$E12,Control_Plantillas!$Z$4:$Z$59),0) -> 0.5 | H12: =COUNTIFS(Control_Plantillas!$B$4:$B$59,$E12,Control_Plantillas!$I$4:$I$59,"Completado") -> 1 | I12: =COUNTIFS(Control_Plantillas!$B$4:$B$59,$E12,Control_Plantillas!$L$4:$L$59,"Completado") -> 0 | J12: =COUNTIFS(Control_Plantillas!$B$4:$B$59,$E12,Control_Plantillas!$O$4:$O$59,"Completado") -> 0 | K12: =COUNTIFS(Control_Plantillas!$B$4:$B$59,$E12,Control_Plantillas!$R$4:$R$59,"Completado") -> 0 | L12: =COUNTIFS(Control_Plantillas!$B$4:$B$59,$E12,Control_Plantillas!$U$4:$U$59,"Completado") -> 0
A13: En riesgo (≤7 días) | C13: =COUNTIF(Control_Plantillas!$AC$4:$AC$59,"En riesgo") -> 0 | E13: TOTAL | F13: =SUM(F7:F12) -> 41 | G13: =IFERROR(AVERAGE(Control_Plantillas!$Z$4:$Z$59),0) -> 0.47195122 | H13: =SUM(H7:H12) -> 23 | I13: =SUM(I7:I12) -> 17 | J13: =SUM(J7:J12) -> 17 | K13: =SUM(K7:K12) -> 0 | L13: =SUM(L7:L12) -> 0
A14: Sin fecha compromiso | C14: =COUNTIF(Control_Plantillas!$AC$4:$AC$59,"Sin fecha") -> 17
A15: Cerradas (productivo) | C15: =COUNTIF(Control_Plantillas!$AC$4:$AC$59,"Cerrado") -> 0
E18: DISTRIBUCIÓN POR ETAPA ACTUAL
E19: Etapa | F19: Plantillas | G19: % del total
E20: 1. Llenado de plantilla | F20: =COUNTIF(Control_Plantillas!$Y$4:$Y$59,$E20) -> 18 | G20: =IFERROR($F20/SUM($F$20:$F$25),0) -> 0.43902439
E21: 2. Revisión y validación | F21: =COUNTIF(Control_Plantillas!$Y$4:$Y$59,$E21) -> 6 | G21: =IFERROR($F21/SUM($F$20:$F$25),0) -> 0.14634146
E22: 3. Carga en repositorio Oracle | F22: =COUNTIF(Control_Plantillas!$Y$4:$Y$59,$E22) -> 0 | G22: =IFERROR($F22/SUM($F$20:$F$25),0) -> 0
E23: 4. Ambiente Sandbox | F23: =COUNTIF(Control_Plantillas!$Y$4:$Y$59,$E23) -> 17 | G23: =IFERROR($F23/SUM($F$20:$F$25),0) -> 0.41463415
E24: 5. Ambiente Productivo | F24: =COUNTIF(Control_Plantillas!$Y$4:$Y$59,$E24) -> 0 | G24: =IFERROR($F24/SUM($F$20:$F$25),0) -> 0
E25: 6. Cerrado | F25: =COUNTIF(Control_Plantillas!$Y$4:$Y$59,$E25) -> 0 | G25: =IFERROR($F25/SUM($F$20:$F$25),0) -> 0

Sheet Instructivo
A1: INSTRUCTIVO DE USO — CONTROL DE PLANTILLAS ORACLE NETSUITE
A3: 1. ¿Qué se captura y qué se calcula solo?
A4: • Celdas con fondo AMARILLO: son las únicas que se capturan manualmente (Key User, Revisor y las fechas de compromiso / reales).
A5: • Columnas de estatus (E1 a E5): se seleccionan de la lista desplegable. No escribir texto libre.
A6: • Columnas X a AC (Etapa #, Etapa Actual, % Avance, Próx. Compromiso, Días Restantes y Semáforo): se calculan automáticamente. NO editar.
A7: • La hoja Resumen_Ejecutivo se actualiza sola a partir de la hoja Control_Plantillas.
A9: 2. Etapas del flujo y su peso en el avance
A10: • E1 · Llenado de plantilla por el área / Key User .................... 40%
A11: • E2 · Revisión y validación (PMO / consultoría) ..................... 20%
A12: • E3 · Carga en el repositorio de Oracle ............................. 15%
A13: • E4 · Carga y validación en ambiente Sandbox ........................ 15%
A14: • E5 · Carga en ambiente Productivo .................................. 10%
... A46: 7. Ejemplo de captura correcta de una fila
A47: ID | C47: VTA-01
A48: Módulo | C48: Ventas (O2C)
A49: Plantilla | C49: 300 MX Clientes (Final)
A50: Key User | C50: Itzel Bárcena
A51: Revisor / Consultor | C51: Brandon Hernández
A52: Prioridad | C52: Crítica
A53: E1 Llenado | C53: Completado
A54: E1 F. Compromiso | C54: 15/05/2026
A55: E1 F. Real | C55: 26/05/2026
A56: E2 Revisión | C56: En proceso
A57: E2 F. Compromiso | C57: 28/08/2026
A58: Observaciones | C58: Duplicidad de RFC entre dos clientes: requiere definición del área.

Sheet Catalogos
A1: CATÁLOGOS - No modificar sin autorización del PMO
A2: Estatus | B2: Factor avance | D2: Módulos | F2: Prioridad | H2: Áreas / Frentes | J2: Etapas | L2: Peso etapa
A3: No iniciado | B3: 0 | D3: Finanzas (R2R) | F3: Crítica | H3: Finanzas / Contabilidad | J3: 1. Llenado de plantilla | L3: 0.4
A4: En proceso | B4: 0.5 | D4: Compras (P2P) | F4: Alta | H4: Compras / Abastecimiento | J4: 2. Revisión y validación | L4: 0.2
A5: Completado | B5: 1 | D5: Ventas (O2C) | F5: Media | H5: Comercial / Ventas | J5: 3. Carga en repositorio Oracle | L5: 0.15
A6: Bloqueado | B6: 0 | D6: Inventarios (D2B) | F6: Baja | H6: Almacén / Inventarios | J6: 4. Ambiente Sandbox | L6: 0.15
A7: No aplica | B7: 1 | D7: Manufactura (MFG) | H7: Manufactura / Producción | J7: 5. Ambiente Productivo | L7: 0.1
D8: Activos Fijos (FA) | H8: Activos Fijos / Patrimonio | J8: 6. Cerrado | L8: 0
H9: Capital Humano | J9: Suma de pesos (debe ser 100%) | L9: =SUM(L3:L7) -> 1
H10: PMO / Consultoría

Sheet Control_Plantillas
A1: CONTROL DE PLANTILLAS DE MIGRACIÓN — ORACLE NETSUITE | ESTEVEZ.JOR
A2: IDENTIFICACIÓN Y RESPONSABLES | I2: E1 · LLENADO | L2: E2 · REVISIÓN | O2: E3 · REPOSITORIO ORACLE | R2: E4 · SANDBOX | U2: E5 · PRODUCTIVO | X2: SEGUIMIENTO AUTOMÁTICO
A3: ID | B3: Módulo | C3: Código | D3: Plantilla | E3: Área Responsable | F3: Key User | G3: Consultor Oracle | H3: Prioridad | I3: E1 Llenado | J3: E1 F. Compromiso | K3: E1 F. Real | L3: E2 Revisión | M3: E2 F. Compromiso | N3: E2 F. Real | O3: E3 Repositorio | P3: E3 F. Compromiso | Q3: E3 F. Real | R3: E4 Sandbox | S3: E4 F. Compromiso | T3: E4 F. Real | U3: E5 Productivo | V3: E5 F. Compromiso | W3: E5 F. Real | X3: Etapa # | Y3: Etapa Actual | Z3: % Avance | AA3: Próx. Compromiso | AB3: Días Restantes | AC3: Semáforo | AD3: Observaciones / Bloqueos
A4: FIN-01 | B4: Finanzas (R2R) | C4: — | D4: ESTEVEZ - Clases | E4: Finanzas / Contabilidad | F4: Angelica Ramirez | G4: Fredy Sanchez | H4: Alta | I4: Completado | J4: 46268 | K4: 46268 | L4: Completado | M4: 46268 | N4: 46268 | O4: Completado | P4: 46268 | Q4: 46268 | R4: No iniciado | U4: No iniciado | X4: =IF(OR($U4="Completado",$U4="No aplica"),6,IF(OR($R4="Completado",$R4="No aplica"),5,IF(OR($O4="Completado",$O4="No aplica"),4,IF(OR($L4="Completado",$L4="No aplica"),3,IF(OR($I4="Completado",$I4="No aplica"),2,1))))) -> 4 | Y4: {=INDEX(Cat_Etapas,$X4)} -> 4. Ambiente Sandbox | Z4: {=ROUND(Catalogos!$L$3*IFERROR(INDEX(Cat_Factor,MATCH($I4,Cat_Estatus,0)),0)+Catalogos!$L$4*IFERROR(INDEX(Cat_Factor,MATCH($L4,Cat_Estatus,0)),0)+Catalogos!$L$5*IFERROR(INDEX(Cat_Factor,MATCH($O4,Cat_Estatus,0)),0)+Catalogos!$L$6*IFERROR(INDEX(Cat_Factor,MATCH($R4,Cat_Estatus,0)),0)+Catalogos!$L$7*IFERROR(INDEX(Cat_Factor,MATCH($U4,Cat_Estatus,0)),0),4)} -> 0.75 | AA4: =IF($X4=6,"",IF(IFERROR(INDEX($I4:$V4,3*$X4-1),0)=0,"",INDEX($I4:$V4,3*$X4-1))) | AB4: =IF($AA4="","",$AA4-TODAY()) | AC4: =IF($X4=6,"Cerrado",IF(OR($I4="Bloqueado",$L4="Bloqueado",$O4="Bloqueado",$R4="Bloqueado",$U4="Bloqueado"),"Bloqueado",IF($AA4="","Sin fecha",IF($AB4<0,"Vencido",IF($AB4<=7,"En riesgo","En tiempo"))))) -> Sin fecha
A5: FIN-02 | B5: Finanzas (R2R) | C5: — | D5: ESTEVEZ - COA MX Plan de Cuentas | E5: Finanzas / Contabilidad | F5: Angelica Ramirez | G5: Fredy Sanchez | H5: Alta | I5: Completado | J5: 46282 | K5: 46298 | L5: Completado | O5: Completado | R5: No iniciado | U5: No iniciado | X5: =IF(OR($U5="Completado",$U5="No aplica"),6,IF(OR($R5="Completado",$R5="No aplica"),5,IF(OR($O5="Completado",$O5="No aplica"),4,IF(OR($L5="Completado",$L5="No aplica"),3,IF(OR($I5="Completado",$I5="No aplica"),2,1))))) -> 4 | Y5: {=INDEX(Cat_Etapas,$X5)} -> 4. Ambiente Sandbox | Z5: {=ROUND(Catalogos!$L$3*IFERROR(INDEX(Cat_Factor,MATCH($I5,Cat_Estatus,0)),0)+Catalogos!$L$4*IFERROR(INDEX(Cat_Factor,MATCH($L5,Cat_Estatus,0)),0)+Catalogos!$L$5*IFERROR(INDEX(Cat_Factor,MATCH($O5,Cat_Estatus,0)),0)+Catalogos!$L$6*IFERROR(INDEX(Cat_Factor,MATCH($R5,Cat_Estatus,0)),0)+Catalogos!$L$7*IFERROR(INDEX(Cat_Factor,MATCH($U5,Cat_Estatus,0)),0),4)} -> 0.75 | AA5: =IF($X5=6,"",IF(IFERROR(INDEX($I5:$V5,3*$X5-1),0)=0,"",INDEX($I5:$V5,3*$X5-1))) | AB5: =IF($AA5="","",$AA5-TODAY()) | AC5: =IF($X5=6,"Cerrado",IF(OR($I5="Bloqueado",$L5="Bloqueado",$O5="Bloqueado",$R5="Bloqueado",$U5="Bloqueado"),"Bloqueado",IF($AA5="","Sin fecha",IF($AB5<0,"Vencido",IF($AB5<=7,"En riesgo","En tiempo"))))) -> Sin fecha
A6: FIN-03 | B6: Finanzas (R2R) | C6: — | D6: ESTEVEZ - Departamentos | E6: Finanzas / Contabilidad | F6: Angelica Ramirez | G6: Fredy Sanchez | H6: Alta | I6: Completado | J6: 46268 | K6: 46268 | L6: Completado | M6: 46268 | N6: 46268 | O6: Completado | P6: 46268 | Q6: 46268 | R6: No iniciado | U6: No iniciado | X6: =IF(OR($U6="Completado",$U6="No aplica"),6,IF(OR($R6="Completado",$R6="No aplica"),5,IF(OR($O6="Completado",$O6="No aplica"),4,IF(OR($L6="Completado",$L6="No aplica"),3,IF(OR($I6="Completado",$I6="No aplica"),2,1))))) -> 4 | Y6: {=INDEX(Cat_Etapas,$X6)} -> 4. Ambiente Sandbox | Z6: {=ROUND(Catalogos!$L$3*IFERROR(INDEX(Cat_Factor,MATCH($I6,Cat_Estatus,0)),0)+Catalogos!$L$4*IFERROR(INDEX(Cat_Factor,MATCH($L6,Cat_Estatus,0)),0)+Catalogos!$L$5*IFERROR(INDEX(Cat_Factor,MATCH($O6,Cat_Estatus,0)),0)+Catalogos!$L$6*IFERROR(INDEX(Cat_Factor,MATCH($R6,Cat_Estatus,0)),0)+Catalogos!$L$7*IFERROR(INDEX(Cat_Factor,MATCH($U6,Cat_Estatus,0)),0),4)} -> 0.75 | AA6: =IF($X6=6,"",IF(IFERROR(INDEX($I6:$V6,3*$X6-1),0)=0,"",INDEX($I6:$V6,3*$X6-1))) | AB6: =IF($AA6="","",$AA6-TODAY()) | AC6: =IF($X6=6,"Cerrado",IF(OR($I6="Bloqueado",$L6="Bloqueado",$O6="Bloqueado",$R6="Bloqueado",$U6="Bloqueado"),"Bloqueado",IF($AA6="","Sin fecha",IF($AB6<0,"Vencido",IF($AB6<=7,"En riesgo","En tiempo"))))) -> Sin fecha
A7: FIN-04 | B7: Finanzas (R2R) | C7: — | D7: ESTEVEZ - Plantilla Subsidiarias | E7: Finanzas / Contabilidad | F7: Angelica Ramirez | G7: Fredy Sanchez | H7: Alta | I7: Completado | J7: 46268 | K7: 46268 | L7: Completado | M7: 46268 | N7: 46268 | O7: Completado | P7: 46268 | Q7: 46268 | R7: No iniciado | U7: No iniciado | X7: =IF(OR($U7="Completado",$U7="No aplica"),6,IF(OR($R7="Completado",$R7="No aplica"),5,IF(OR($O7="Completado",$O7="No aplica"),4,IF(OR($L7="Completado",$L7="No aplica"),3,IF(OR($I7="Completado",$I7="No aplica"),2,1))))) -> 4 | Y7: {=INDEX(Cat_Etapas,$X7)} -> 4. Ambiente Sandbox | Z7: {=ROUND(Catalogos!$L$3*IFERROR(INDEX(Cat_Factor,MATCH($I7,Cat_Estatus,0)),0)+Catalogos!$L$4*IFERROR(INDEX(Cat_Factor,MATCH($L7,Cat_Estatus,0)),0)+Catalogos!$L$5*IFERROR(INDEX(Cat_Factor,MATCH($O7,Cat_Estatus,0)),0)+Catalogos!$L$6*IFERROR(INDEX(Cat_Factor,MATCH($R7,Cat_Estatus,0)),0)+Catalogos!$L$7*IFERROR(INDEX(Cat_Factor,MATCH($U7,Cat_Estatus,0)),0),4)} -> 0.75 | AA7: =IF($X7=6,"",IF(IFERROR(INDEX($I7:$V7,3*$X7-1),0)=0,"",INDEX($I7:$V7,3*$X7-1))) | AB7: =IF($AA7="","",$AA7-TODAY()) | AC7: =IF($X7=6,"Cerrado",IF(OR($I7="Bloqueado",$L7="Bloqueado",$O7="Bloqueado",$R7="Bloqueado",$U7="Bloqueado"),"Bloqueado",IF($AA7="","Sin fecha",IF($AB7<0,"Vencido",IF($AB7<=7,"En riesgo","En tiempo"))))) -> Sin fecha
A8: FIN-05 | B8: Finanzas (R2R) | C8: — | D8: ESTEVEZ - Ubicaciones | E8: Finanzas / Contabilidad | F8: Angelica Ramirez | G8: Fredy Sanchez | H8: Alta | I8: Completado | J8: 46302 | L8: Completado | M8: 46283 | N8: 46283 | O8: Completado | P8: 46283 | Q8: 46283 | R8: No iniciado | U8: No iniciado | X8: =IF(OR($U8="Completado",$U8="No aplica"),6,IF(OR($R8="Completado",$R8="No aplica"),5,IF(OR($O8="Completado",$O8="No aplica"),4,IF(OR($L8="Completado",$L8="No aplica"),3,IF(OR($I8="Completado",$I8="No aplica"),2,1))))) -> 4 | Y8: {=INDEX(Cat_Etapas,$X8)} -> 4. Ambiente Sandbox | Z8: {=ROUND(Catalogos!$L$3*IFERROR(INDEX(Cat_Factor,MATCH($I8,Cat_Estatus,0)),0)+Catalogos!$L$4*IFERROR(INDEX(Cat_Factor,MATCH($L8,Cat_Estatus,0)),0)+Catalogos!$L$5*IFERROR(INDEX(Cat_Factor,MATCH($O8,Cat_Estatus,0)),0)+Catalogos!$L$6*IFERROR(INDEX(Cat_Factor,MATCH($R8,Cat_Estatus,0)),0)+Catalogos!$L$7*IFERROR(INDEX(Cat_Factor,MATCH($U8,Cat_Estatus,0)),0),4)} -> 0.75 | AA8: =IF($X8=6,"",IF(IFERROR(INDEX($I8:$V8,3*$X8-1),0)=0,"",INDEX($I8:$V8,3*$X8-1))) | AB8: =IF($AA8="","",$AA8-TODAY()) | AC8: =IF($X8=6,"Cerrado",IF(OR($I8="Bloqueado",$L8="Bloqueado",$O8="Bloqueado",$R8="Bloqueado",$U8="Bloqueado"),"Bloqueado",IF($AA8="","Sin fecha",IF($AB8<0,"Vencido",IF($AB8<=7,"En riesgo","En tiempo"))))) -> Sin fecha
A9: FIN-06 | B9: Finanzas (R2R) | C9: — | D9: ESTEVEZ - Impuestos y Retenciones MX | E9: Finanzas / Contabilidad | F9: Angelica Ramirez | G9: Fredy Sanchez | H9: Alta | I9: Completado | J9: 46274 | K9: 46274 | L9: Completado | M9: 46277 | N9: 46277 | O9: Completado | P9: 46277 | Q9: 46277 | R9: No iniciado | U9: No iniciado | X9: =IF(OR($U9="Completado",$U9="No aplica"),6,IF(OR($R9="Completado",$R9="No aplica"),5,IF(OR($O9="Completado",$O9="No aplica"),4,IF(OR($L9="Completado",$L9="No aplica"),3,IF(OR($I9="Completado",$I9="No aplica"),2,1))))) -> 4 | Y9: {=INDEX(Cat_Etapas,$X9)} -> 4. Ambiente Sandbox | Z9: {=ROUND(Catalogos!$L$3*IFERROR(INDEX(Cat_Factor,MATCH($I9,Cat_Estatus,0)),0)+Catalogos!$L$4*IFERROR(INDEX(Cat_Factor,MATCH($L9,Cat_Estatus,0)),0)+Catalogos!$L$5*IFERROR(INDEX(Cat_Factor,MATCH($O9,Cat_Estatus,0)),0)+Catalogos!$L$6*IFERROR(INDEX(Cat_Factor,MATCH($R9,Cat_Estatus,0)),0)+Catalogos!$L$7*IFERROR(INDEX(Cat_Factor,MATCH($U9,Cat_Estatus,0)),0),4)} -> 0.75 | AA9: =IF($X9=6,"",IF(IFERROR(INDEX($I9:$V9,3*$X9-1),0)=0,"",INDEX($I9:$V9,3*$X9-1))) | AB9: =IF($AA9="","",$AA9-TODAY()) | AC9: =IF($X9=6,"Cerrado",IF(OR($I9="Bloqueado",$L9="Bloqueado",$O9="Bloqueado",$R9="Bloqueado",$U9="Bloqueado"),"Bloqueado",IF($AA9="","Sin fecha",IF($AB9<0,"Vencido",IF($AB9<=7,"En riesgo","En tiempo"))))) -> Sin fecha
A10: CMP-01 | B10: Compras (P2P) | C10: 210 | D10: Proveedores | E10: Compras / Abastecimiento | F10: Nancy Ruiz Ruiz Ana Laura Cedillo | G10: Hector Garcia | H10: Alta | I10: Completado | J10: 46272 | K10: 46272 | L10: Completado | M10: 46277 | N10: 46277 | O10: Completado | P10: 46277 | R10: No iniciado | U10: No iniciado | X10: =IF(OR($U10="Completado",$U10="No aplica"),6,IF(OR($R10="Completado",$R10="No aplica"),5,IF(OR($O10="Completado",$O10="No aplica"),4,IF(OR($L10="Completado",$L10="No aplica"),3,IF(OR($I10="Completado",$I10="No aplica"),2,1))))) -> 4 | Y10: {=INDEX(Cat_Etapas,$X10)} -> 4. Ambiente Sandbox | Z10: {=ROUND(Catalogos!$L$3*IFERROR(INDEX(Cat_Factor,MATCH($I10,Cat_Estatus,0)),0)+Catalogos!$L$4*IFERROR(INDEX(Cat_Factor,MATCH($L10,Cat_Estatus,0)),0)+Catalogos!$L$5*IFERROR(INDEX(Cat_Factor,MATCH($O10,Cat_Estatus,0)),0)+Catalogos!$L$6*IFERROR(INDEX(Cat_Factor,MATCH($R10,Cat_Estatus,0)),0)+Catalogos!$L$7*IFERROR(INDEX(Cat_Factor,MATCH($U10,Cat_Estatus,0)),0),4)} -> 0.75 | AA10: =IF($X10=6,"",IF(IFERROR(INDEX($I10:$V10,3*$X10-1),0)=0,"",INDEX($I10:$V10,3*$X10-1))) | AB10: =IF($AA10="","",$AA10-TODAY()) | AC10: =IF($X10=6,"Cerrado",IF(OR($I10="Bloqueado",$L10="Bloqueado",$O10="Bloqueado",$R10="Bloqueado",$U10="Bloqueado"),"Bloqueado",IF($AA10="","Sin fecha",IF($AB10<0,"Vencido",IF($AB10<=7,"En riesgo","En tiempo"))))) -> Sin fecha
A11: CMP-02 | B11: Compras (P2P) | C11: 220 | D11: Empleados | E11: Capital Humano | F11: Caterrine Ladino | G11: Hector Garcia | H11: Alta | I11: Completado | J11: 46268 | K11: 46268 | L11: Completado | M11: 46269 | N11: 46269 | O11: Completado | P11: 46269 | Q11: 46269 | R11: No iniciado | U11: No iniciado | X11: =IF(OR($U11="Completado",$U11="No aplica"),6,IF(OR($R11="Completado",$R11="No aplica"),5,IF(OR($O11="Completado",$O11="No aplica"),4,IF(OR($L11="Completado",$L11="No aplica"),3,IF(OR($I11="Completado",$I11="No aplica"),2,1))))) -> 4 | Y11: {=INDEX(Cat_Etapas,$X11)} -> 4. Ambiente Sandbox | Z11: {=ROUND(Catalogos!$L$3*IFERROR(INDEX(Cat_Factor,MATCH($I11,Cat_Estatus,0)),0)+Catalogos!$L$4*IFERROR(INDEX(Cat_Factor,MATCH($L11,Cat_Estatus,0)),0)+Catalogos!$L$5*IFERROR(INDEX(Cat_Factor,MATCH($O11,Cat_Estatus,0)),0)+Catalogos!$L$6*IFERROR(INDEX(Cat_Factor,MATCH($R11,Cat_Estatus,0)),0)+Catalogos!$L$7*IFERROR(INDEX(Cat_Factor,MATCH($U11,Cat_Estatus,0)),0),4)} -> 0.75 | AA11: =IF($X11=6,"",IF(IFERROR(INDEX($I11:$V11,3*$X11-1),0)=0,"",INDEX($I11:$V11,3*$X11-1))) | AB11: =IF($AA11="","",$AA11-TODAY()) | AC11: =IF($X11=6,"Cerrado",IF(OR($I11="Bloqueado",$L11="Bloqueado",$O11="Bloqueado",$R11="Bloqueado",$U11="Bloqueado"),"Bloqueado",IF($AA11="","Sin fecha",IF($AB11<0,"Vencido",IF($AB11<=7,"En riesgo","En tiempo"))))) -> Sin fecha
A12: VTA-01 | B12: Ventas (O2C) | C12: 300 | D12: MX Clientes | E12: Comercial / Ventas | F12: Itzel Barcena Erick Carmona | G12: Jose Mauricio Caranza | H12: Alta | I12: Completado | J12: 46274 | K12: 46274 | L12: Completado | M12: 46277 | O12: Completado | P12: 46276 | R12: No iniciado | U12: No iniciado | X12: =IF(OR($U12="Completado",$U12="No aplica"),6,IF(OR($R12="Completado",$R12="No aplica"),5,IF(OR($O12="Completado",$O12="No aplica"),4,IF(OR($L12="Completado",$L12="No aplica"),3,IF(OR($I12="Completado",$I12="No aplica"),2,1))))) -> 4 | Y12: {=INDEX(Cat_Etapas,$X12)} -> 4. Ambiente Sandbox | Z12: {=ROUND(Catalogos!$L$3*IFERROR(INDEX(Cat_Factor,MATCH($I12,Cat_Estatus,0)),0)+Catalogos!$L$4*IFERROR(INDEX(Cat_Factor,MATCH($L12,Cat_Estatus,0)),0)+Catalogos!$L$5*IFERROR(INDEX(Cat_Factor,MATCH($O12,Cat_Estatus,0)),0)+Catalogos!$L$6*IFERROR(INDEX(Cat_Factor,MATCH($R12,Cat_Estatus,0)),0)+Catalogos!$L$7*IFERROR(INDEX(Cat_Factor,MATCH($U12,Cat_Estatus,0)),0),4)} -> 0.75 | AA12: =IF($X12=6,"",IF(IFERROR(INDEX($I12:$V12,3*$X12-1),0)=0,"",INDEX($I12:$V12,3*$X12-1))) | AB12: =IF($AA12="","",$AA12-TODAY()) | AC12: =IF($X12=6,"Cerrado",IF(OR($I12="Bloqueado",$L12="Bloqueado",$O12="Bloqueado",$R12="Bloqueado",$U12="Bloqueado"),"Bloqueado",IF($AA12="","Sin fecha",IF($AB12<0,"Vencido",IF($AB12<=7,"En riesgo","En tiempo"))))) -> Sin fecha
A13: VTA-02 | B13: Ventas (O2C) | C13: 310 | D13: MX Contactos | E13: Comercial / Ventas | F13: Itzel Barcena Erick Carmona | G13: Jose Mauricio Caranza | H13: Alta | I13: Completado | J13: 46277 | K13: 46303 | L13: Completado | M13: 46277 | O13: Completado | P13: 46276 | R13: No iniciado | U13: No iniciado | X13: =IF(OR($U13="Completado",$U13="No aplica"),6,IF(OR($R13="Completado",$R13="No aplica"),5,IF(OR($O13="Completado",$O13="No aplica"),4,IF(OR($L13="Completado",$L13="No aplica"),3,IF(OR($I13="Completado",$I13="No aplica"),2,1))))) -> 4 | Y13: {=INDEX(Cat_Etapas,$X13)} -> 4. Ambiente Sandbox | Z13: {=ROUND(Catalogos!$L$3*IFERROR(INDEX(Cat_Factor,MATCH($I13,Cat_Estatus,0)),0)+Catalogos!$L$4*IFERROR(INDEX(Cat_Factor,MATCH($L13,Cat_Estatus,0)),0)+Catalogos!$L$5*IFERROR(INDEX(Cat_Factor,MATCH($O13,Cat_Estatus,0)),0)+Catalogos!$L$6*IFERROR(INDEX(Cat_Factor,MATCH($R13,Cat_Estatus,0)),0)+Catalogos!$L$7*IFERROR(INDEX(Cat_Factor,MATCH($U13,Cat_Estatus,0)),0),4)} -> 0.75 | AA13: =IF($X13=6,"",IF(IFERROR(INDEX($I13:$V13,3*$X13-1),0)=0,"",INDEX($I13:$V13,3*$X13-1))) | AB13: =IF($AA13="","",$AA13-TODAY()) | AC13: =IF($X13=6,"Cerrado",IF(OR($I13="Bloqueado",$L13="Bloqueado",$O13="Bloqueado",$R13="Bloqueado",$U13="Bloqueado"),"Bloqueado",IF($AA13="","Sin fecha",IF($AB13<0,"Vencido",IF($AB13<=7,"En riesgo","En tiempo"))))) -> Sin fecha
A14: VTA-03 | B14: Ventas (O2C) | C14: 320 | D14: MX Direcciones | E14: Comercial / Ventas | F14: Itzel Barcena Erick Carmona | G14: Jose Mauricio Caranza | H14: Alta | I14: Completado | J14: 46277 | L14: Completado | M14: 46283 | O14: Completado | P14: 46276 | R14: No iniciado | U14: No iniciado | X14: =IF(OR($U14="Completado",$U14="No aplica"),6,IF(OR($R14="Completado",$R14="No aplica"),5,IF(OR($O14="Completado",$O14="No aplica"),4,IF(OR($L14="Completado",$L14="No aplica"),3,IF(OR($I14="Completado",$I14="No aplica"),2,1))))) -> 4 | Y14: {=INDEX(Cat_Etapas,$X14)} -> 4. Ambiente Sandbox | Z14: {=ROUND(Catalogos!$L$3*IFERROR(INDEX(Cat_Factor,MATCH($I14,Cat_Estatus,0)),0)+Catalogos!$L$4*IFERROR(INDEX(Cat_Factor,MATCH($L14,Cat_Estatus,0)),0)+Catalogos!$L$5*IFERROR(INDEX(Cat_Factor,MATCH($O14,Cat_Estatus,0)),0)+Catalogos!$L$6*IFERROR(INDEX(Cat_Factor,MATCH($R14,Cat_Estatus,0)),0)+Catalogos!$L$7*IFERROR(INDEX(Cat_Factor,MATCH($U14,Cat_Estatus,0)),0),4)} -> 0.75 | AA14: =IF($X14=6,"",IF(IFERROR(INDEX($I14:$V14,3*$X14-1),0)=0,"",INDEX($I14:$V14,3*$X14-1))) | AB14: =IF($AA14="","",$AA14-TODAY()) | AC14: =IF($X14=6,"Cerrado",IF(OR($I14="Bloqueado",$L14="Bloqueado",$O14="Bloqueado",$R14="Bloqueado",$U14="Bloqueado"),"Bloqueado",IF($AA14="","Sin fecha",IF($AB14<0,"Vencido",IF($AB14<=7,"En riesgo","En tiempo"))))) -> Sin fecha
A15: INV-01 | B15: Inventarios (D2B) | C15: 401 | D15: MX Unidades de Medida | E15: Almacén / Inventarios | F15: Edgar Manuel Avila | G15: Mateo Escallón | H15: Alta | I15: Completado | J15: 46283 | L15: En proceso | M15: 46283 | O15: No iniciado | P15: 46276 | R15: No iniciado | U15: No iniciado | X15: =IF(OR($U15="Completado",$U15="No aplica"),6,IF(OR($R15="Completado",$R15="No aplica"),5,IF(OR($O15="Completado",$O15="No aplica"),4,IF(OR($L15="Completado",$L15="No aplica"),3,IF(OR($I15="Completado",$I15="No aplica"),2,1))))) -> 2 | Y15: {=INDEX(Cat_Etapas,$X15)} -> 2. Revisión y validación | Z15: {=ROUND(Catalogos!$L$3*IFERROR(INDEX(Cat_Factor,MATCH($I15,Cat_Estatus,0)),0)+Catalogos!$L$4*IFERROR(INDEX(Cat_Factor,MATCH($L15,Cat_Estatus,0)),0)+Catalogos!$L$5*IFERROR(INDEX(Cat_Factor,MATCH($O15,Cat_Estatus,0)),0)+Catalogos!$L$6*IFERROR(INDEX(Cat_Factor,MATCH($R15,Cat_Estatus,0)),0)+Catalogos!$L$7*IFERROR(INDEX(Cat_Factor,MATCH($U15,Cat_Estatus,0)),0),4)} -> 0.5 | AA15: =IF($X15=6,"",IF(IFERROR(INDEX($I15:$V15,3*$X15-1),0)=0,"",INDEX($I15:$V15,3*$X15-1))) -> 46283 | AB15: =IF($AA15="","",$AA15-TODAY()) -> -24 | AC15: =IF($X15=6,"Cerrado",IF(OR($I15="Bloqueado",$L15="Bloqueado",$O15="Bloqueado",$R15="Bloqueado",$U15="Bloqueado"),"Bloqueado",IF($AA15="","Sin fecha",IF($AB15<0,"Vencido",IF($AB15<=7,"En riesgo","En tiempo"))))) -> Vencido
A16: INV-02 | B16: Inventarios (D2B) | C16: 402 | D16: MX SAT Clave Producto Servicio | E16: Almacén / Inventarios | F16: Edgar Manuel Avila | G16: Mateo Escallón | H16: Alta | I16: Completado | J16: 46283 | L16: En proceso | M16: 46283 | O16: No iniciado | P16: 46276 | R16: No iniciado | U16: No iniciado | X16: =IF(OR($U16="Completado",$U16="No aplica"),6,IF(OR($R16="Completado",$R16="No aplica"),5,IF(OR($O16="Completado",$O16="No aplica"),4,IF(OR($L16="Completado",$L16="No aplica"),3,IF(OR($I16="Completado",$I16="No aplica"),2,1))))) -> 2 | Y16: {=INDEX(Cat_Etapas,$X16)} -> 2. Revisión y validación | Z16: {=ROUND(Catalogos!$L$3*IFERROR(INDEX(Cat_Factor,MATCH($I16,Cat_Estatus,0)),0)+Catalogos!$L$4*IFERROR(INDEX(Cat_Factor,MATCH($L16,Cat_Estatus,0)),0)+Catalogos!$L$5*IFERROR(INDEX(Cat_Factor,MATCH($O16,Cat_Estatus,0)),0)+Catalogos!$L$6*IFERROR(INDEX(Cat_Factor,MATCH($R16,Cat_Estatus,0)),0)+Catalogos!$L$7*IFERROR(INDEX(Cat_Factor,MATCH($U16,Cat_Estatus,0)),0),4)} -> 0.5 | AA16: =IF($X16=6,"",IF(IFERROR(INDEX($I16:$V16,3*$X16-1),0)=0,"",INDEX($I16:$V16,3*$X16-1))) -> 46283 | AB16: =IF($AA16="","",$AA16-TODAY()) -> -24 | AC16: =IF($X16=6,"Cerrado",IF(OR($I16="Bloqueado",$L16="Bloqueado",$O16="Bloqueado",$R16="Bloqueado",$U16="Bloqueado"),"Bloqueado",IF($AA16="","Sin fecha",IF($AB16<0,"Vencido",IF($AB16<=7,"En riesgo","En tiempo"))))) -> Vencido
A17: INV-03 | B17: Inventarios (D2B) | C17: 403 | D17: MX SAT Clave de Unidad | E17: Almacén / Inventarios | F17: Edgar Manuel Avila | G17: Mateo Escallón | H17: Alta | I17: Completado | J17: 46283 | L17: En proceso | M17: 46283 | O17: No iniciado | P17: 46276 | R17: No iniciado | U17: No iniciado | X17: =IF(OR($U17="Completado",$U17="No aplica"),6,IF(OR($R17="Completado",$R17="No aplica"),5,IF(OR($O17="Completado",$O17="No aplica"),4,IF(OR($L17="Completado",$L17="No aplica"),3,IF(OR($I17="Completado",$I17="No aplica"),2,1))))) -> 2 | Y17: {=INDEX(Cat_Etapas,$X17)} -> 2. Revisión y validación | Z17: {=ROUND(Catalogos!$L$3*IFERROR(INDEX(Cat_Factor,MATCH($I17,Cat_Estatus,0)),0)+Catalogos!$L$4*IFERROR(INDEX(Cat_Factor,MATCH($L17,Cat_Estatus,0)),0)+Catalogos!$L$5*IFERROR(INDEX(Cat_Factor,MATCH($O17,Cat_Estatus,0)),0)+Catalogos!$L$6*IFERROR(INDEX(Cat_Factor,MATCH($R17,Cat_Estatus,0)),0)+Catalogos!$L$7*IFERROR(INDEX(Cat_Factor,MATCH($U17,Cat_Estatus,0)),0),4)} -> 0.5 | AA17: =IF($X17=6,"",IF(IFERROR(INDEX($I17:$V17,3*$X17-1),0)=0,"",INDEX($I17:$V17,3*$X17-1))) -> 46283 | AB17: =IF($AA17="","",$AA17-TODAY()) -> -24 | AC17: =IF($X17=6,"Cerrado",IF(OR($I17="Bloqueado",$L17="Bloqueado",$O17="Bloqueado",$R17="Bloqueado",$U17="Bloqueado"),"Bloqueado",IF($AA17="","Sin fecha",IF($AB17<0,"Vencido",IF($AB17<=7,"En riesgo","En tiempo"))))) -> Vencido
A18: INV-04 | B18: Inventarios (D2B) | C18: 404 | D18: MX SAT Clave Arancelaria | E18: Almacén / Inventarios | F18: Edgar Manuel Avila | G18: Mateo Escallón | H18: Alta | I18: En proceso | J18: 46283 | L18: No iniciado | M18: 46283 | O18: No iniciado | P18: 46276 | R18: No iniciado | U18: No iniciado | X18: =IF(OR($U18="Completado",$U18="No aplica"),6,IF(OR($R18="Completado",$R18="No aplica"),5,IF(OR($O18="Completado",$O18="No aplica"),4,IF(OR($L18="Completado",$L18="No aplica"),3,IF(OR($I18="Completado",$I18="No aplica"),2,1))))) -> 1 | Y18: {=INDEX(Cat_Etapas,$X18)} -> 1. Llenado de plantilla | Z18: {=ROUND(Catalogos!$L$3*IFERROR(INDEX(Cat_Factor,MATCH($I18,Cat_Estatus,0)),0)+Catalogos!$L$4*IFERROR(INDEX(Cat_Factor,MATCH($L18,Cat_Estatus,0)),0)+Catalogos!$L$5*IFERROR(INDEX(Cat_Factor,MATCH($O18,Cat_Estatus,0)),0)+Catalogos!$L$6*IFERROR(INDEX(Cat_Factor,MATCH($R18,Cat_Estatus,0)),0)+Catalogos!$L$7*IFERROR(INDEX(Cat_Factor,MATCH($U18,Cat_Estatus,0)),0),4)} -> 0.2 | AA18: =IF($X18=6,"",IF(IFERROR(INDEX($I18:$V18,3*$X18-1),0)=0,"",INDEX($I18:$V18,3*$X18-1))) -> 46283 | AB18: =IF($AA18="","",$AA18-TODAY()) -> -24 | AC18: =IF($X18=6,"Cerrado",IF(OR($I18="Bloqueado",$L18="Bloqueado",$O18="Bloqueado",$R18="Bloqueado",$U18="Bloqueado"),"Bloqueado",IF($AA18="","Sin fecha",IF($AB18<0,"Vencido",IF($AB18<=7,"En riesgo","En tiempo"))))) -> Vencido
A19: INV-05 | B19: Inventarios (D2B) | C19: 410 | D19: MX Artículo de Inventario | E19: Almacén / Inventarios | F19: Edgar Manuel Avila | G19: Mateo Escallón | H19: Alta | I19: Completado | J19: 46283 | L19: En proceso | M19: 46283 | O19: No iniciado | P19: 46276 | R19: No iniciado | U19: No iniciado | X19: =IF(OR($U19="Completado",$U19="No aplica"),6,IF(OR($R19="Completado",$R19="No aplica"),5,IF(OR($O19="Completado",$O19="No aplica"),4,IF(OR($L19="Completado",$L19="No aplica"),3,IF(OR($I19="Completado",$I19="No aplica"),2,1))))) -> 2 | Y19: {=INDEX(Cat_Etapas,$X19)} -> 2. Revisión y validación | Z19: {=ROUND(Catalogos!$L$3*IFERROR(INDEX(Cat_Factor,MATCH($I19,Cat_Estatus,0)),0)+Catalogos!$L$4*IFERROR(INDEX(Cat_Factor,MATCH($L19,Cat_Estatus,0)),0)+Catalogos!$L$5*IFERROR(INDEX(Cat_Factor,MATCH($O19,Cat_Estatus,0)),0)+Catalogos!$L$6*IFERROR(INDEX(Cat_Factor,MATCH($R19,Cat_Estatus,0)),0)+Catalogos!$L$7*IFERROR(INDEX(Cat_Factor,MATCH($U19,Cat_Estatus,0)),0),4)} -> 0.5 | AA19: =IF($X19=6,"",IF(IFERROR(INDEX($I19:$V19,3*$X19-1),0)=0,"",INDEX($I19:$V19,3*$X19-1))) -> 46283 | AB19: =IF($AA19="","",$AA19-TODAY()) -> -24 | AC19: =IF($X19=6,"Cerrado",IF(OR($I19="Bloqueado",$L19="Bloqueado",$O19="Bloqueado",$R19="Bloqueado",$U19="Bloqueado"),"Bloqueado",IF($AA19="","Sin fecha",IF($AB19<0,"Vencido",IF($AB19<=7,"En riesgo","En tiempo"))))) -> Vencido
A20: INV-06 | B20: Inventarios (D2B) | C20: 411 | D20: MX Artículo Fuera de Inventario para la Compra | E20: Almacén / Inventarios | F20: Edgar Manuel Avila | G20: Mateo Escallón | H20: Alta | I20: En proceso | J20: 46283 | L20: No iniciado | M20: 46283 | O20: No iniciado | P20: 46276 | R20: No iniciado | U20: No iniciado | X20: =IF(OR($U20="Completado",$U20="No aplica"),6,IF(OR($R20="Completado",$R20="No aplica"),5,IF(OR($O20="Completado",$O20="No aplica"),4,IF(OR($L20="Completado",$L20="No aplica"),3,IF(OR($I20="Completado",$I20="No aplica"),2,1))))) -> 1 | Y20: {=INDEX(Cat_Etapas,$X20)} -> 1. Llenado de plantilla | Z20: {=ROUND(Catalogos!$L$3*IFERROR(INDEX(Cat_Factor,MATCH($I20,Cat_Estatus,0)),0)+Catalogos!$L$4*IFERROR(INDEX(Cat_Factor,MATCH($L20,Cat_Estatus,0)),0)+Catalogos!$L$5*IFERROR(INDEX(Cat_Factor,MATCH($O20,Cat_Estatus,0)),0)+Catalogos!$L$6*IFERROR(INDEX(Cat_Factor,MATCH($R20,Cat_Estatus,0)),0)+Catalogos!$L$7*IFERROR(INDEX(Cat_Factor,MATCH($U20,Cat_Estatus,0)),0),4)} -> 0.2 | AA20: =IF($X20=6,"",IF(IFERROR(INDEX($I20:$V20,3*$X20-1),0)=0,"",INDEX($I20:$V20,3*$X20-1))) -> 46283 | AB20: =IF($AA20="","",$AA20-TODAY()) -> -24 | AC20: =IF($X20=6,"Cerrado",IF(OR($I20="Bloqueado",$L20="Bloqueado",$O20="Bloqueado",$R20="Bloqueado",$U20="Bloqueado"),"Bloqueado",IF($AA20="","Sin fecha",IF($AB20<0,"Vencido",IF($AB20<=7,"En riesgo","En tiempo"))))) -> Vencido
A21: INV-07 | B21: Inventarios (D2B) | C21: 412 | D21: MX Artículo Fuera de Inventario para la Venta | E21: Almacén / Inventarios | F21: Edgar Manuel Avila | G21: Mateo Escallón | H21: Alta | I21: Completado | J21: 46283 | L21: En proceso | M21: 46283 | O21: No iniciado | P21: 46276 | R21: No iniciado | U21: No iniciado | X21: =IF(OR($U21="Completado",$U21="No aplica"),6,IF(OR($R21="Completado",$R21="No aplica"),5,IF(OR($O21="Completado",$O21="No aplica"),4,IF(OR($L21="Completado",$L21="No aplica"),3,IF(OR($I21="Completado",$I21="No aplica"),2,1))))) -> 2 | Y21: {=INDEX(Cat_Etapas,$X21)} -> 2. Revisión y validación | Z21: {=ROUND(Catalogos!$L$3*IFERROR(INDEX(Cat_Factor,MATCH($I21,Cat_Estatus,0)),0)+Catalogos!$L$4*IFERROR(INDEX(Cat_Factor,MATCH($L21,Cat_Estatus,0)),0)+Catalogos!$L$5*IFERROR(INDEX(Cat_Factor,MATCH($O21,Cat_Estatus,0)),0)+Catalogos!$L$6*IFERROR(INDEX(Cat_Factor,MATCH($R21,Cat_Estatus,0)),0)+Catalogos!$L$7*IFERROR(INDEX(Cat_Factor,MATCH($U21,Cat_Estatus,0)),0),4)} -> 0.5 | AA21: =IF($X21=6,"",IF(IFERROR(INDEX($I21:$V21,3*$X21-1),0)=0,"",INDEX($I21:$V21,3*$X21-1))) -> 46283 | AB21: =IF($AA21="","",$AA21-TODAY()) -> -24 | AC21: =IF($X21=6,"Cerrado",IF(OR($I21="Bloqueado",$L21="Bloqueado",$O21="Bloqueado",$R21="Bloqueado",$U21="Bloqueado"),"Bloqueado",IF($AA21="","Sin fecha",IF($AB21<0,"Vencido",IF($AB21<=7,"En riesgo","En tiempo"))))) -> Vencido
A22: INV-08 | B22: Inventarios (D2B) | C22: 413 | D22: MX Artículo Fuera de Inventario para la Reventa | E22: Almacén / Inventarios | F22: Edgar Manuel Avila | G22: Mateo Escallón | H22: Alta | I22: En proceso | J22: 46283 | L22: No iniciado | M22: 46283 | O22: No iniciado | P22: 46276 | R22: No iniciado | U22: No iniciado | X22: =IF(OR($U22="Completado",$U22="No aplica"),6,IF(OR($R22="Completado",$R22="No aplica"),5,IF(OR($O22="Completado",$O22="No aplica"),4,IF(OR($L22="Completado",$L22="No aplica"),3,IF(OR($I22="Completado",$I22="No aplica"),2,1))))) -> 1 | Y22: {=INDEX(Cat_Etapas,$X22)} -> 1. Llenado de plantilla | Z22: {=ROUND(Catalogos!$L$3*IFERROR(INDEX(Cat_Factor,MATCH($I22,Cat_Estatus,0)),0)+Catalogos!$L$4*IFERROR(INDEX(Cat_Factor,MATCH($L22,Cat_Estatus,0)),0)+Catalogos!$L$5*IFERROR(INDEX(Cat_Factor,MATCH($O22,Cat_Estatus,0)),0)+Catalogos!$L$6*IFERROR(INDEX(Cat_Factor,MATCH($R22,Cat_Estatus,0)),0)+Catalogos!$L$7*IFERROR(INDEX(Cat_Factor,MATCH($U22,Cat_Estatus,0)),0),4)} -> 0.2 | AA22: =IF($X22=6,"",IF(IFERROR(INDEX($I22:$V22,3*$X22-1),0)=0,"",INDEX($I22:$V22,3*$X22-1))) -> 46283 | AB22: =IF($AA22="","",$AA22-TODAY()) -> -24 | AC22: =IF($X22=6,"Cerrado",IF(OR($I22="Bloqueado",$L22="Bloqueado",$O22="Bloqueado",$R22="Bloqueado",$U22="Bloqueado"),"Bloqueado",IF($AA22="","Sin fecha",IF($AB22<0,"Vencido",IF($AB22<=7,"En riesgo","En tiempo"))))) -> Vencido
A23: INV-09 | B23: Inventarios (D2B) | C23: 414 | D23: MX Artículo con Descuento | E23: Almacén / Inventarios | F23: Edgar Manuel Avila | G23: Mateo Escallón | H23: Alta | I23: En proceso | J23: 46283 | L23: No iniciado | M23: 46283 | O23: No iniciado | P23: 46276 | R23: No iniciado | U23: No iniciado | X23: =IF(OR($U23="Completado",$U23="No aplica"),6,IF(OR($R23="Completado",$R23="No aplica"),5,IF(OR($O23="Completado",$O23="No aplica"),4,IF(OR($L23="Completado",$L23="No aplica"),3,IF(OR($I23="Completado",$I23="No aplica"),2,1))))) -> 1 | Y23: {=INDEX(Cat_Etapas,$X23)} -> 1. Llenado de plantilla | Z23: {=ROUND(Catalogos!$L$3*IFERROR(INDEX(Cat_Factor,MATCH($I23,Cat_Estatus,0)),0)+Catalogos!$L$4*IFERROR(INDEX(Cat_Factor,MATCH($L23,Cat_Estatus,0)),0)+Catalogos!$L$5*IFERROR(INDEX(Cat_Factor,MATCH($O23,Cat_Estatus,0)),0)+Catalogos!$L$6*IFERROR(INDEX(Cat_Factor,MATCH($R23,Cat_Estatus,0)),0)+Catalogos!$L$7*IFERROR(INDEX(Cat_Factor,MATCH($U23,Cat_Estatus,0)),0),4)} -> 0.2 | AA23: =IF($X23=6,"",IF(IFERROR(INDEX($I23:$V23,3*$X23-1),0)=0,"",INDEX($I23:$V23,3*$X23-1))) -> 46283 | AB23: =IF($AA23="","",$AA23-TODAY()) -> -24 | AC23: =IF($X23=6,"Cerrado",IF(OR($I23="Bloqueado",$L23="Bloqueado",$O23="Bloqueado",$R23="Bloqueado",$U23="Bloqueado"),"Bloqueado",IF($AA23="","Sin fecha",IF($AB23<0,"Vencido",IF($AB23<=7,"En riesgo","En tiempo"))))) -> Vencido
A24: INV-10 | B24: Inventarios (D2B) | C24: 415 | D24: MX Artículo con Recargo | E24: Almacén / Inventarios | F24: Edgar Manuel Avila | G24: Mateo Escallón | H24: Alta | I24: En proceso | J24: 46283 | L24: No iniciado | M24: 46283 | O24: No iniciado | P24: 46276 | R24: No iniciado | U24: No iniciado | X24: =IF(OR($U24="Completado",$U24="No aplica"),6,IF(OR($R24="Completado",$R24="No aplica"),5,IF(OR($O24="Completado",$O24="No aplica"),4,IF(OR($L24="Completado",$L24="No aplica"),3,IF(OR($I24="Completado",$I24="No aplica"),2,1))))) -> 1 | Y24: {=INDEX(Cat_Etapas,$X24)} -> 1. Llenado de plantilla | Z24: {=ROUND(Catalogos!$L$3*IFERROR(INDEX(Cat_Factor,MATCH($I24,Cat_Estatus,0)),0)+Catalogos!$L$4*IFERROR(INDEX(Cat_Factor,MATCH($L24,Cat_Estatus,0)),0)+Catalogos!$L$5*IFERROR(INDEX(Cat_Factor,MATCH($O24,Cat_Estatus,0)),0)+Catalogos!$L$6*IFERROR(INDEX(Cat_Factor,MATCH($R24,Cat_Estatus,0)),0)+Catalogos!$L$7*IFERROR(INDEX(Cat_Factor,MATCH($U24,Cat_Estatus,0)),0),4)} -> 0.2 | AA24: =IF($X24=6,"",IF(IFERROR(INDEX($I24:$V24,3*$X24-1),0)=0,"",INDEX($I24:$V24,3*$X24-1))) -> 46283 | AB24: =IF($AA24="","",$AA24-TODAY()) -> -24 | AC24: =IF($X24=6,"Cerrado",IF(OR($I24="Bloqueado",$L24="Bloqueado",$O24="Bloqueado",$R24="Bloqueado",$U24="Bloqueado"),"Bloqueado",IF($AA24="","Sin fecha",IF($AB24<0,"Vencido",IF($AB24<=7,"En riesgo","En tiempo"))))) -> Vencido
A25: INV-11 | B25: Inventarios (D2B) | C25: 416 | D25: MX Artículo de Servicio para la Compra | E25: Almacén / Inventarios | F25: Edgar Manuel Avila | G25: Mateo Escallón | H25: Alta | I25: En proceso | J25: 46283 | L25: No iniciado | M25: 46283 | O25: No iniciado | P25: 46276 | R25: No iniciado | U25: No iniciado | X25: =IF(OR($U25="Completado",$U25="No aplica"),6,IF(OR($R25="Completado",$R25="No aplica"),5,IF(OR($O25="Completado",$O25="No aplica"),4,IF(OR($L25="Completado",$L25="No aplica"),3,IF(OR($I25="Completado",$I25="No aplica"),2,1))))) -> 1 | Y25: {=INDEX(Cat_Etapas,$X25)} -> 1. Llenado de plantilla | Z25: {=ROUND(Catalogos!$L$3*IFERROR(INDEX(Cat_Factor,MATCH($I25,Cat_Estatus,0)),0)+Catalogos!$L$4*IFERROR(INDEX(Cat_Factor,MATCH($L25,Cat_Estatus,0)),0)+Catalogos!$L$5*IFERROR(INDEX(Cat_Factor,MATCH($O25,Cat_Estatus,0)),0)+Catalogos!$L$6*IFERROR(INDEX(Cat_Factor,MATCH($R25,Cat_Estatus,0)),0)+Catalogos!$L$7*IFERROR(INDEX(Cat_Factor,MATCH($U25,Cat_Estatus,0)),0),4)} -> 0.2 | AA25: =IF($X25=6,"",IF(IFERROR(INDEX($I25:$V25,3*$X25-1),0)=0,"",INDEX($I25:$V25,3*$X25-1))) -> 46283 | AB25: =IF($AA25="","",$AA25-TODAY()) -> -24 | AC25: =IF($X25=6,"Cerrado",IF(OR($I25="Bloqueado",$L25="Bloqueado",$O25="Bloqueado",$R25="Bloqueado",$U25="Bloqueado"),"Bloqueado",IF($AA25="","Sin fecha",IF($AB25<0,"Vencido",IF($AB25<=7,"En riesgo","En tiempo"))))) -> Vencido
... A37: INV-23 | B37: Inventarios (D2B) | C37: 472 | D37: MX Costo de Revaluación de Inventario | E37: Almacén / Inventarios | F37: Edgar Manuel Avila | G37: Mateo Escallón | H37: Alta | I37: En proceso | J37: 46283 | L37: No iniciado | M37: 46283 | O37: No iniciado | P37: 46276 | R37: No iniciado | U37: No iniciado | X37: =IF(OR($U37="Completado",$U37="No aplica"),6,IF(OR($R37="Completado",$R37="No aplica"),5,IF(OR($O37="Completado",$O37="No aplica"),4,IF(OR($L37="Completado",$L37="No aplica"),3,IF(OR($I37="Completado",$I37="No aplica"),2,1))))) -> 1 | Y37: {=INDEX(Cat_Etapas,$X37)} -> 1. Llenado de plantilla | Z37: {=ROUND(Catalogos!$L$3*IFERROR(INDEX(Cat_Factor,MATCH($I37,Cat_Estatus,0)),0)+Catalogos!$L$4*IFERROR(INDEX(Cat_Factor,MATCH($L37,Cat_Estatus,0)),0)+Catalogos!$L$5*IFERROR(INDEX(Cat_Factor,MATCH($O37,Cat_Estatus,0)),0)+Catalogos!$L$6*IFERROR(INDEX(Cat_Factor,MATCH($R37,Cat_Estatus,0)),0)+Catalogos!$L$7*IFERROR(INDEX(Cat_Factor,MATCH($U37,Cat_Estatus,0)),0),4)} -> 0.2 | AA37: =IF($X37=6,"",IF(IFERROR(INDEX($I37:$V37,3*$X37-1),0)=0,"",INDEX($I37:$V37,3*$X37-1))) -> 46283 | AB37: =IF($AA37="","",$AA37-TODAY()) -> -24 | AC37: =IF($X37=6,"Cerrado",IF(OR($I37="Bloqueado",$L37="Bloqueado",$O37="Bloqueado",$R37="Bloqueado",$U37="Bloqueado"),"Bloqueado",IF($AA37="","Sin fecha",IF($AB37<0,"Vencido",IF($AB37<=7,"En riesgo","En tiempo"))))) -> Vencido
A38: MFG-01 | B38: Manufactura (MFG) | C38: 410 | D38: MX Artículo de Inventario Manufactura | E38: Manufactura / Producción | F38: Alberto Romero | G38: Mateo Escallón | H38: Alta | I38: Completado | J38: 46277 | K38: 46276 | L38: Completado | M38: 46283 | O38: Completado | P38: 46277 | R38: No iniciado | U38: No iniciado | X38: =IF(OR($U38="Completado",$U38="No aplica"),6,IF(OR($R38="Completado",$R38="No aplica"),5,IF(OR($O38="Completado",$O38="No aplica"),4,IF(OR($L38="Completado",$L38="No aplica"),3,IF(OR($I38="Completado",$I38="No aplica"),2,1))))) -> 4 | Y38: {=INDEX(Cat_Etapas,$X38)} -> 4. Ambiente Sandbox | Z38: {=ROUND(Catalogos!$L$3*IFERROR(INDEX(Cat_Factor,MATCH($I38,Cat_Estatus,0)),0)+Catalogos!$L$4*IFERROR(INDEX(Cat_Factor,MATCH($L38,Cat_Estatus,0)),0)+Catalogos!$L$5*IFERROR(INDEX(Cat_Factor,MATCH($O38,Cat_Estatus,0)),0)+Catalogos!$L$6*IFERROR(INDEX(Cat_Factor,MATCH($R38,Cat_Estatus,0)),0)+Catalogos!$L$7*IFERROR(INDEX(Cat_Factor,MATCH($U38,Cat_Estatus,0)),0),4)} -> 0.75 | AA38: =IF($X38=6,"",IF(IFERROR(INDEX($I38:$V38,3*$X38-1),0)=0,"",INDEX($I38:$V38,3*$X38-1))) | AB38: =IF($AA38="","",$AA38-TODAY()) | AC38: =IF($X38=6,"Cerrado",IF(OR($I38="Bloqueado",$L38="Bloqueado",$O38="Bloqueado",$R38="Bloqueado",$U38="Bloqueado"),"Bloqueado",IF($AA38="","Sin fecha",IF($AB38<0,"Vencido",IF($AB38<=7,"En riesgo","En tiempo"))))) -> Sin fecha
A39: MFG-02 | B39: Manufactura (MFG) | C39: 500 | D39: Artículos Otros Cargos para la Compra | E39: Manufactura / Producción | F39: Alberto Romero | G39: Mateo Escallón | H39: Alta | I39: Completado | J39: 46283 | L39: Completado | M39: 46283 | O39: Completado | P39: 46283 | R39: No iniciado | U39: No iniciado | X39: =IF(OR($U39="Completado",$U39="No aplica"),6,IF(OR($R39="Completado",$R39="No aplica"),5,IF(OR($O39="Completado",$O39="No aplica"),4,IF(OR($L39="Completado",$L39="No aplica"),3,IF(OR($I39="Completado",$I39="No aplica"),2,1))))) -> 4 | Y39: {=INDEX(Cat_Etapas,$X39)} -> 4. Ambiente Sandbox | Z39: {=ROUND(Catalogos!$L$3*IFERROR(INDEX(Cat_Factor,MATCH($I39,Cat_Estatus,0)),0)+Catalogos!$L$4*IFERROR(INDEX(Cat_Factor,MATCH($L39,Cat_Estatus,0)),0)+Catalogos!$L$5*IFERROR(INDEX(Cat_Factor,MATCH($O39,Cat_Estatus,0)),0)+Catalogos!$L$6*IFERROR(INDEX(Cat_Factor,MATCH($R39,Cat_Estatus,0)),0)+Catalogos!$L$7*IFERROR(INDEX(Cat_Factor,MATCH($U39,Cat_Estatus,0)),0),4)} -> 0.75 | AA39: =IF($X39=6,"",IF(IFERROR(INDEX($I39:$V39,3*$X39-1),0)=0,"",INDEX($I39:$V39,3*$X39-1))) | AB39: =IF($AA39="","",$AA39-TODAY()) | AC39: =IF($X39=6,"Cerrado",IF(OR($I39="Bloqueado",$L39="Bloqueado",$O39="Bloqueado",$R39="Bloqueado",$U39="Bloqueado"),"Bloqueado",IF($AA39="","Sin fecha",IF($AB39<0,"Vencido",IF($AB39<=7,"En riesgo","En tiempo"))))) -> Sin fecha
A40: MFG-03 | B40: Manufactura (MFG) | C40: 510 | D40: Listas de Materiales | E40: Manufactura / Producción | F40: Alberto Romero | G40: Mateo Escallón | H40: Alta | I40: Completado | J40: 46283 | L40: Completado | M40: 46283 | O40: Completado | P40: 46283 | R40: No iniciado | U40: No iniciado | X40: =IF(OR($U40="Completado",$U40="No aplica"),6,IF(OR($R40="Completado",$R40="No aplica"),5,IF(OR($O40="Completado",$O40="No aplica"),4,IF(OR($L40="Completado",$L40="No aplica"),3,IF(OR($I40="Completado",$I40="No aplica"),2,1))))) -> 4 | Y40: {=INDEX(Cat_Etapas,$X40)} -> 4. Ambiente Sandbox | Z40: {=ROUND(Catalogos!$L$3*IFERROR(INDEX(Cat_Factor,MATCH($I40,Cat_Estatus,0)),0)+Catalogos!$L$4*IFERROR(INDEX(Cat_Factor,MATCH($L40,Cat_Estatus,0)),0)+Catalogos!$L$5*IFERROR(INDEX(Cat_Factor,MATCH($O40,Cat_Estatus,0)),0)+Catalogos!$L$6*IFERROR(INDEX(Cat_Factor,MATCH($R40,Cat_Estatus,0)),0)+Catalogos!$L$7*IFERROR(INDEX(Cat_Factor,MATCH($U40,Cat_Estatus,0)),0),4)} -> 0.75 | AA40: =IF($X40=6,"",IF(IFERROR(INDEX($I40:$V40,3*$X40-1),0)=0,"",INDEX($I40:$V40,3*$X40-1))) | AB40: =IF($AA40="","",$AA40-TODAY()) | AC40: =IF($X40=6,"Cerrado",IF(OR($I40="Bloqueado",$L40="Bloqueado",$O40="Bloqueado",$R40="Bloqueado",$U40="Bloqueado"),"Bloqueado",IF($AA40="","Sin fecha",IF($AB40<0,"Vencido",IF($AB40<=7,"En riesgo","En tiempo"))))) -> Sin fecha
A41: MFG-04 | B41: Manufactura (MFG) | C41: 520 | D41: Revisión de Listas de Materiales Estándar | E41: Manufactura / Producción | F41: Alberto Romero | G41: Mateo Escallón | H41: Alta | I41: Completado | J41: 46283 | L41: Completado | M41: 46283 | O41: Completado | P41: 46283 | R41: No iniciado | U41: No iniciado | X41: =IF(OR($U41="Completado",$U41="No aplica"),6,IF(OR($R41="Completado",$R41="No aplica"),5,IF(OR($O41="Completado",$O41="No aplica"),4,IF(OR($L41="Completado",$L41="No aplica"),3,IF(OR($I41="Completado",$I41="No aplica"),2,1))))) -> 4 | Y41: {=INDEX(Cat_Etapas,$X41)} -> 4. Ambiente Sandbox | Z41: {=ROUND(Catalogos!$L$3*IFERROR(INDEX(Cat_Factor,MATCH($I41,Cat_Estatus,0)),0)+Catalogos!$L$4*IFERROR(INDEX(Cat_Factor,MATCH($L41,Cat_Estatus,0)),0)+Catalogos!$L$5*IFERROR(INDEX(Cat_Factor,MATCH($O41,Cat_Estatus,0)),0)+Catalogos!$L$6*IFERROR(INDEX(Cat_Factor,MATCH($R41,Cat_Estatus,0)),0)+Catalogos!$L$7*IFERROR(INDEX(Cat_Factor,MATCH($U41,Cat_Estatus,0)),0),4)} -> 0.75 | AA41: =IF($X41=6,"",IF(IFERROR(INDEX($I41:$V41,3*$X41-1),0)=0,"",INDEX($I41:$V41,3*$X41-1))) | AB41: =IF($AA41="","",$AA41-TODAY()) | AC41: =IF($X41=6,"Cerrado",IF(OR($I41="Bloqueado",$L41="Bloqueado",$O41="Bloqueado",$R41="Bloqueado",$U41="Bloqueado"),"Bloqueado",IF($AA41="","Sin fecha",IF($AB41<0,"Vencido",IF($AB41<=7,"En riesgo","En tiempo"))))) -> Sin fecha
A42: MFG-05 | B42: Manufactura (MFG) | C42: 530 | D42: Artículos de Ensamble Lotizados | E42: Manufactura / Producción | F42: Alberto Romero | G42: Mateo Escallón | H42: Alta | I42: Completado | J42: 46283 | L42: Completado | M42: 46283 | O42: Completado | P42: 46283 | R42: No iniciado | U42: No iniciado | X42: =IF(OR($U42="Completado",$U42="No aplica"),6,IF(OR($R42="Completado",$R42="No aplica"),5,IF(OR($O42="Completado",$O42="No aplica"),4,IF(OR($L42="Completado",$L42="No aplica"),3,IF(OR($I42="Completado",$I42="No aplica"),2,1))))) -> 4 | Y42: {=INDEX(Cat_Etapas,$X42)} -> 4. Ambiente Sandbox | Z42: {=ROUND(Catalogos!$L$3*IFERROR(INDEX(Cat_Factor,MATCH($I42,Cat_Estatus,0)),0)+Catalogos!$L$4*IFERROR(INDEX(Cat_Factor,MATCH($L42,Cat_Estatus,0)),0)+Catalogos!$L$5*IFERROR(INDEX(Cat_Factor,MATCH($O42,Cat_Estatus,0)),0)+Catalogos!$L$6*IFERROR(INDEX(Cat_Factor,MATCH($R42,Cat_Estatus,0)),0)+Catalogos!$L$7*IFERROR(INDEX(Cat_Factor,MATCH($U42,Cat_Estatus,0)),0),4)} -> 0.75 | AA42: =IF($X42=6,"",IF(IFERROR(INDEX($I42:$V42,3*$X42-1),0)=0,"",INDEX($I42:$V42,3*$X42-1))) | AB42: =IF($AA42="","",$AA42-TODAY()) | AC42: =IF($X42=6,"Cerrado",IF(OR($I42="Bloqueado",$L42="Bloqueado",$O42="Bloqueado",$R42="Bloqueado",$U42="Bloqueado"),"Bloqueado",IF($AA42="","Sin fecha",IF($AB42<0,"Vencido",IF($AB42<=7,"En riesgo","En tiempo"))))) -> Sin fecha
A43: MFG-06 | B43: Manufactura (MFG) | C43: 540 | D43: Artículos de Ensamble | E43: Manufactura / Producción | F43: Alberto Romero | G43: Mateo Escallón | H43: Alta | I43: Completado | J43: 46277 | K43: 46276 | L43: Completado | M43: 46277 | N43: 46276 | O43: Completado | P43: 46276 | Q43: 46277 | R43: No iniciado | U43: No iniciado | X43: =IF(OR($U43="Completado",$U43="No aplica"),6,IF(OR($R43="Completado",$R43="No aplica"),5,IF(OR($O43="Completado",$O43="No aplica"),4,IF(OR($L43="Completado",$L43="No aplica"),3,IF(OR($I43="Completado",$I43="No aplica"),2,1))))) -> 4 | Y43: {=INDEX(Cat_Etapas,$X43)} -> 4. Ambiente Sandbox | Z43: {=ROUND(Catalogos!$L$3*IFERROR(INDEX(Cat_Factor,MATCH($I43,Cat_Estatus,0)),0)+Catalogos!$L$4*IFERROR(INDEX(Cat_Factor,MATCH($L43,Cat_Estatus,0)),0)+Catalogos!$L$5*IFERROR(INDEX(Cat_Factor,MATCH($O43,Cat_Estatus,0)),0)+Catalogos!$L$6*IFERROR(INDEX(Cat_Factor,MATCH($R43,Cat_Estatus,0)),0)+Catalogos!$L$7*IFERROR(INDEX(Cat_Factor,MATCH($U43,Cat_Estatus,0)),0),4)} -> 0.75 | AA43: =IF($X43=6,"",IF(IFERROR(INDEX($I43:$V43,3*$X43-1),0)=0,"",INDEX($I43:$V43,3*$X43-1))) | AB43: =IF($AA43="","",$AA43-TODAY()) | AC43: =IF($X43=6,"Cerrado",IF(OR($I43="Bloqueado",$L43="Bloqueado",$O43="Bloqueado",$R43="Bloqueado",$U43="Bloqueado"),"Bloqueado",IF($AA43="","Sin fecha",IF($AB43<0,"Vencido",IF($AB43<=7,"En riesgo","En tiempo"))))) -> Sin fecha
A44: ACF-01 | B44: Activos Fijos (FA) | C44: 600 | D44: Tipos de Activo Fijo | E44: Activos Fijos / Patrimonio | F44: Angelica Ramirez | G44: Fredy Sanchez | H44: Alta | I44: Completado | J44: 46277 | K44: 46275 | L44: En proceso | M44: 46276 | O44: No iniciado | R44: No iniciado | U44: No iniciado | X44: =IF(OR($U44="Completado",$U44="No aplica"),6,IF(OR($R44="Completado",$R44="No aplica"),5,IF(OR($O44="Completado",$O44="No aplica"),4,IF(OR($L44="Completado",$L44="No aplica"),3,IF(OR($I44="Completado",$I44="No aplica"),2,1))))) -> 2 | Y44: {=INDEX(Cat_Etapas,$X44)} -> 2. Revisión y validación | Z44: {=ROUND(Catalogos!$L$3*IFERROR(INDEX(Cat_Factor,MATCH($I44,Cat_Estatus,0)),0)+Catalogos!$L$4*IFERROR(INDEX(Cat_Factor,MATCH($L44,Cat_Estatus,0)),0)+Catalogos!$L$5*IFERROR(INDEX(Cat_Factor,MATCH($O44,Cat_Estatus,0)),0)+Catalogos!$L$6*IFERROR(INDEX(Cat_Factor,MATCH($R44,Cat_Estatus,0)),0)+Catalogos!$L$7*IFERROR(INDEX(Cat_Factor,MATCH($U44,Cat_Estatus,0)),0),4)} -> 0.5 | AA44: =IF($X44=6,"",IF(IFERROR(INDEX($I44:$V44,3*$X44-1),0)=0,"",INDEX($I44:$V44,3*$X44-1))) -> 46276 | AB44: =IF($AA44="","",$AA44-TODAY()) -> -31 | AC44: =IF($X44=6,"Cerrado",IF(OR($I44="Bloqueado",$L44="Bloqueado",$O44="Bloqueado",$R44="Bloqueado",$U44="Bloqueado"),"Bloqueado",IF($AA44="","Sin fecha",IF($AB44<0,"Vencido",IF($AB44<=7,"En riesgo","En tiempo"))))) -> Vencido
